joulegl/__init__.py
joulegl/opengl_helper/__init__.py
joulegl/opengl_helper/buffer.py
joulegl/opengl_helper/frame_buffer.py
joulegl/opengl_helper/screenshot.py
joulegl/opengl_helper/texture.py
joulegl/opengl_helper/vertex_data_handler.py
joulegl/opengl_helper/base/__init__.py
joulegl/opengl_helper/base/config.py
joulegl/opengl_helper/base/data_set.py
joulegl/opengl_helper/base/shader.py
joulegl/opengl_helper/base/shader_handler.py
joulegl/opengl_helper/base/shader_parser.py
joulegl/opengl_helper/compute/__init__.py
joulegl/opengl_helper/compute/shader.py
joulegl/opengl_helper/compute/shader_handler.py
joulegl/opengl_helper/render/__init__.py
joulegl/opengl_helper/render/config.py
joulegl/opengl_helper/render/shader.py
joulegl/opengl_helper/render/shader_handler.py
joulegl/opengl_helper/render/utility.py
joulegl/processing/__init__.py
joulegl/processing/processor.py
joulegl/rendering/__init__.py
joulegl/rendering/renderer.py
joulegl/utility/__init__.py
joulegl/utility/app.py
joulegl/utility/camera.py
joulegl/utility/config.py
joulegl/utility/definitions.py
joulegl/utility/file.py
joulegl/utility/glcontext.py
joulegl/utility/input_handler.py
joulegl/utility/log_handling.py
joulegl/utility/performance.py
joulegl/utility/singleton.py
joulegl/utility/window.py
joulegl/utility/window_config.py
joulegl-1.0.0.dist-info/LICENSE
joulegl-1.0.0.dist-info/METADATA
joulegl-1.0.0.dist-info/WHEEL
joulegl-1.0.0.dist-info/top_level.txt
joulegl-1.0.0.dist-info/RECORD
