Metadata-Version: 2.1
Name: joulegl
Version: 1.0.0
Summary: Low level rendering framework using OpenGL python bindings.
Author-email: Nojoule <nojoule0@gmail.com>
License: MIT License
Project-URL: Repository, https://github.com/nojoule/joulegl
Classifier: Programming Language :: Python :: 3
Classifier: License :: OSI Approved :: MIT License
Classifier: Operating System :: OS Independent
Requires-Python: >=3.10
License-File: LICENSE
Requires-Dist: aiohttp ==3.10.5
Requires-Dist: glfw ==2.7.0
Requires-Dist: numpy ==1.26.4
Requires-Dist: PyOpenGL ==3.1.7
Requires-Dist: Pillow ==9.5.0
Provides-Extra: dev
Requires-Dist: pytest ==8.3.2 ; extra == 'dev'
Requires-Dist: pytest-cov ==5.0.0 ; extra == 'dev'
